LICENSE
MANIFEST.in
README.rst
setup.py
Mopidy_dam1021.egg-info/PKG-INFO
Mopidy_dam1021.egg-info/SOURCES.txt
Mopidy_dam1021.egg-info/dependency_links.txt
Mopidy_dam1021.egg-info/entry_points.txt
Mopidy_dam1021.egg-info/not-zip-safe
Mopidy_dam1021.egg-info/requires.txt
Mopidy_dam1021.egg-info/top_level.txt
mopidy_dam1021/__init__.py
mopidy_dam1021/ext.conf
mopidy_dam1021/mixer.py