Metadata-Version: 1.1
Name: Mopidy-dam1021
Version: 0.4
Summary: Mopidy extension for controlling volume on a dam1021 DAC
Home-page: https://github.com/fortaa/mopidy-dam1021
Author: Forta(a)
Author-email: fortaa@users.noreply.github.com
License: Apache License, Version 2.0
Download-URL: https://github.com/fortaa/mopidy-dam1021/tarball/0.4
Platform: UNKNOWN
Classifier: Environment :: No Input/Output (Daemon)
Classifier: Intended Audience :: End Users/Desktop
Classifier: License :: OSI Approved :: Apache Software License
Classifier: Operating System :: OS Independent
Classifier: Programming Language :: Python :: 2
Classifier: Topic :: Multimedia :: Sound/Audio :: Players
